<?xml version="1.0" encoding="UTF-8"?>
<mule xmlns="http://www.mulesoft.org/schema/mule/core" xmlns:apikit="http://www.mulesoft.org/schema/mule/mule-apikit" xmlns:doc="http://www.mulesoft.org/schema/mule/documentation" xmlns:ee="http://www.mulesoft.org/schema/mule/ee/core" xmlns:http="http://www.mulesoft.org/schema/mule/http" xmlns:xsi="http://www.w3.org/2001/XMLSchema-instance" xsi:schemaLocation="http://www.mulesoft.org/schema/mule/core http://www.mulesoft.org/schema/mule/core/current/mule.xsd http://www.mulesoft.org/schema/mule/http http://www.mulesoft.org/schema/mule/http/current/mule-http.xsd http://www.mulesoft.org/schema/mule/mule-apikit http://www.mulesoft.org/schema/mule/mule-apikit/current/mule-apikit.xsd http://www.mulesoft.org/schema/mule/ee/core http://www.mulesoft.org/schema/mule/ee/core/current/mule-ee.xsd ">
    
    <flow name="retrivefastgoroutesandschedules-systemapi-main">
        <http:listener config-ref="retrivefastgoroutesandschedules-systemapi-httpListenerConfig" path="/api/*">
            <http:response statusCode="#[vars.httpStatus default 200]">
                <http:headers>#[vars.outboundHeaders default {}]</http:headers>
            </http:response>
            <http:error-response statusCode="#[vars.httpStatus default 500]">
                <http:body>#[payload]</http:body>
                <http:headers>#[vars.outboundHeaders default {}]</http:headers>
            </http:error-response>
        </http:listener>
        <apikit:router config-ref="retrivefastgoroutesandschedules-systemapi-config" />
        <error-handler>
            <on-error-propagate type="APIKIT:BAD_REQUEST">
                <ee:transform doc:name="Transform Message">
                    <ee:message>
                        <ee:set-payload><![CDATA[%dw 2.0
output application/json
---
{message: "Bad request"}]]></ee:set-payload>
                    </ee:message>
                    <ee:variables>
                        <ee:set-variable variableName="httpStatus">400</ee:set-variable>
                    </ee:variables>
                </ee:transform>
            </on-error-propagate>
            <on-error-propagate type="APIKIT:NOT_FOUND">
                <ee:transform doc:name="Transform Message">
                    <ee:message>
                        <ee:set-payload><![CDATA[%dw 2.0
output application/json
---
{message: "Resource not found"}]]></ee:set-payload>
                    </ee:message>
                    <ee:variables>
                        <ee:set-variable variableName="httpStatus">404</ee:set-variable>
                    </ee:variables>
                </ee:transform>
            </on-error-propagate>
            <on-error-propagate type="APIKIT:METHOD_NOT_ALLOWED">
                <ee:transform doc:name="Transform Message">
                    <ee:message>
                        <ee:set-payload><![CDATA[%dw 2.0
output application/json
---
{message: "Method not allowed"}]]></ee:set-payload>
                    </ee:message>
                    <ee:variables>
                        <ee:set-variable variableName="httpStatus">405</ee:set-variable>
                    </ee:variables>
                </ee:transform>
            </on-error-propagate>
            <on-error-propagate type="APIKIT:NOT_ACCEPTABLE">
                <ee:transform doc:name="Transform Message">
                    <ee:message>
                        <ee:set-payload><![CDATA[%dw 2.0
output application/json
---
{message: "Not acceptable"}]]></ee:set-payload>
                    </ee:message>
                    <ee:variables>
                        <ee:set-variable variableName="httpStatus">406</ee:set-variable>
                    </ee:variables>
                </ee:transform>
            </on-error-propagate>
            <on-error-propagate type="APIKIT:UNSUPPORTED_MEDIA_TYPE">
                <ee:transform doc:name="Transform Message">
                    <ee:message>
                        <ee:set-payload><![CDATA[%dw 2.0
output application/json
---
{message: "Unsupported media type"}]]></ee:set-payload>
                    </ee:message>
                    <ee:variables>
                        <ee:set-variable variableName="httpStatus">415</ee:set-variable>
                    </ee:variables>
                </ee:transform>
            </on-error-propagate>
            <on-error-propagate type="APIKIT:NOT_IMPLEMENTED">
                <ee:transform doc:name="Transform Message">
                    <ee:message>
                        <ee:set-payload><![CDATA[%dw 2.0
output application/json
---
{message: "Not Implemented"}]]></ee:set-payload>
                    </ee:message>
                    <ee:variables>
                        <ee:set-variable variableName="httpStatus">501</ee:set-variable>
                    </ee:variables>
                </ee:transform>
            </on-error-propagate>
        </error-handler>
    </flow>
    <flow name="retrivefastgoroutesandschedules-systemapi-console">
        <http:listener config-ref="retrivefastgoroutesandschedules-systemapi-httpListenerConfig" path="/console/*">
            <http:response statusCode="#[vars.httpStatus default 200]">
                <http:headers>#[vars.outboundHeaders default {}]</http:headers>
            </http:response>
            <http:error-response statusCode="#[vars.httpStatus default 500]">
                <http:body>#[payload]</http:body>
                <http:headers>#[vars.outboundHeaders default {}]</http:headers>
            </http:error-response>
        </http:listener>
        <apikit:console config-ref="retrivefastgoroutesandschedules-systemapi-config" />
        <error-handler>
            <on-error-propagate type="APIKIT:NOT_FOUND">
                <ee:transform doc:name="Transform Message">
                    <ee:message>
                        <ee:set-payload><![CDATA[%dw 2.0
output application/json
---
{message: "Resource not found"}]]></ee:set-payload>
                    </ee:message>
                    <ee:variables>
                        <ee:set-variable variableName="httpStatus">404</ee:set-variable>
                    </ee:variables>
                </ee:transform>
            </on-error-propagate>
        </error-handler>
    </flow>
    <flow name="get:\(transportType)\(transportCompany)\routes:retrivefastgoroutesandschedules-systemapi-config">
        <logger level="INFO" doc:name="Request Received For GetRoutes" doc:id="a02c91a8-8122-4bce-a92f-59e1c2f39482" message="Request Received For GetRoutes TransactionId : #[vars.transactionId]"/>
		<ee:transform doc:name="Vars">
            <ee:variables>
                <ee:set-variable variableName="transportType"><![CDATA[attributes.uriParams.'transportType']]></ee:set-variable>
                <ee:set-variable variableName="transportCompany"><![CDATA[attributes.uriParams.'transportCompany']]></ee:set-variable>
				<ee:set-variable variableName="transactionId" ><![CDATA[%dw 2.0
output application/java
---
attributes.headers.transactionId]]></ee:set-variable>
            </ee:variables>
        </ee:transform>
		<flow-ref doc:name="Flow Reference To fastGo-getRoutes-implementationSub_Flow" doc:id="de57e2c5-7129-4d07-8297-26a4e3dfa699" name="fastGo-getRoutes-implementationSub_Flow"/>
		<logger level="INFO" doc:name="Response Received For GetRoutes" doc:id="ee00ffbd-e939-4a6a-894d-6fda73e6c863" message="Response Received For GetRoutes TransactionId : #[vars.transactionId]"/>
    </flow>
    <flow name="get:\(transportType)\(transportCompany)\schedules:retrivefastgoroutesandschedules-systemapi-config">
        <logger level="INFO" doc:name="Request Received For GetSchedules" doc:id="406b9aeb-5792-4108-88eb-b73c65dba70b" message="Request Received For GetSchedules TransactionId : #[vars.transactionId]"/>
		<ee:transform doc:name="Vars">
            <ee:variables>
                <ee:set-variable variableName="transportType"><![CDATA[attributes.uriParams.'transportType']]></ee:set-variable>
                <ee:set-variable variableName="transportCompany"><![CDATA[attributes.uriParams.'transportCompany']]></ee:set-variable>
				<ee:set-variable variableName="transactionId" ><![CDATA[%dw 2.0
output application/java
---
attributes.headers.transactionId]]></ee:set-variable>
            </ee:variables>
        </ee:transform>
		<flow-ref doc:name="Flow Reference To fastGo-getSchedules-implementationSub_Flow" doc:id="1aeac4b3-a78f-4599-b288-88e4042f167c" name="fastGo-getSchedules-implementationSub_Flow"/>
		<logger level="INFO" doc:name="Response Received For GetSchedules" doc:id="82166798-ff3a-4aae-be87-842d0a59b261" message="Response Received For GetSchedules TransactionId : #[vars.transactionId]"/>
    </flow>
</mule>
